Lab 6/k_lut_block.v
// --------------------------------------------------------
// Component 1: Shift Register / Configuration Memory
// --------------------------------------------------------
module shift_register(
    input clk,
    input in_0, in_1, in_2, in_3,
    output reg [3:0] q
);
    // Loads the truth table bits into the configuration register
    always @(posedge clk) begin
        q <= {in_3, in_2, in_1, in_0};
    end
endmodule

// --------------------------------------------------------
// Component 2: 4:1 Multiplexer
// --------------------------------------------------------
module mux_4to1(
    input [3:0] data,
    input [1:0] sel,
    output reg out
);
    // Selects the bit of the truth table based on inputs (f_sel)
    always @(*) begin
        case(sel)
            2'b00: out = data[0];
            2'b01: out = data[1];
            2'b10: out = data[2];
            2'b11: out = data[3];
        endcase
    end
endmodule

// --------------------------------------------------------
// Component 3: 1:2 Demultiplexer
// --------------------------------------------------------
module demux_1to2(
    input in,
    input sel,
    output reg out0, // Routes to combinational output
    output reg out1  // Routes to flip-flop
);
    // Routes signal based on 'is_synced'
    always @(*) begin
        if (sel == 1'b0) begin
            out0 = in;
            out1 = 1'b0;
        end else begin
            out0 = 1'b0;
            out1 = in;
        end
    end
endmodule

// --------------------------------------------------------
// Component 4: Output D Flip-Flop
// --------------------------------------------------------
module d_ff(
    input clk,
    input d,
    output reg q
);
    always @(posedge clk) begin
        q <= d;
    end
endmodule

// --------------------------------------------------------
// Component 5: Top-Level K-LUT Architecture
// --------------------------------------------------------
module k_lut_block(
    input In_0,
    input In_1,
    input In_2,
    input In_3,
    input [1:0] f_sel,
    input is_synced,
    input clk,
    output out,
    output out_ff
);
    wire [3:0] config_data;
    wire mux_out;
    wire dff_in;

    // Instantiate Config Memory
    shift_register sr_inst (
        .clk(clk),
        .in_0(In_0), .in_1(In_1), .in_2(In_2), .in_3(In_3),
        .q(config_data)
    );

    // Instantiate 4:1 MUX
    mux_4to1 mux_inst (
        .data(config_data),
        .sel(f_sel),
        .out(mux_out)
    );

    // Instantiate 1:2 DEMUX
    demux_1to2 demux_inst (
        .in(mux_out),
        .sel(is_synced),
        .out0(out),
        .out1(dff_in)
    );

    // Instantiate Output FF
    d_ff dff_inst (
        .clk(clk),
        .d(dff_in),
        .q(out_ff)
    );

endmodule

Lab 6/k_lut_tb.v
`timescale 1ns / 1ps

module k_lut_tb;
    // Testbench signals
    reg In_0, In_1, In_2, In_3;
    reg [1:0] f_sel;
    reg is_synced;
    reg clk;
    
    wire out;
    wire out_ff;

    // Instantiate the Unit Under Test (UUT)
    k_lut_block uut (
        .In_0(In_0), .In_1(In_1), .In_2(In_2), .In_3(In_3),
        .f_sel(f_sel), .is_synced(is_synced), .clk(clk),
        .out(out), .out_ff(out_ff)
    );

    // Clock Generation
    initial clk = 0;
    always #5 clk = ~clk;

    initial begin
        // Setup GTKWave dump
        $dumpfile("k_lut.vcd");
        $dumpvars(0, k_lut_tb);

        // Initialize Inputs
        {In_3, In_2, In_1, In_0} = 4'b0000;
        f_sel = 2'b00;
        is_synced = 0;

        @(negedge clk);
        
        // 1. Test AND Gate (Truth Table: 1000)
        $display("--- Testing AND Gate ---");
        {In_3, In_2, In_1, In_0} = 4'b1000;
        @(negedge clk); // Wait 1 cycle for config to load into Shift Register
        test_all_combos();

        // 2. Test OR Gate (Truth Table: 1110)
        $display("--- Testing OR Gate ---");
        {In_3, In_2, In_1, In_0} = 4'b1110;
        @(negedge clk);
        test_all_combos();

        // 3. Test NAND Gate (Truth Table: 0111)
        $display("--- Testing NAND Gate ---");
        {In_3, In_2, In_1, In_0} = 4'b0111;
        @(negedge clk);
        test_all_combos();

        // 4. Test NOR Gate (Truth Table: 0001)
        $display("--- Testing NOR Gate ---");
        {In_3, In_2, In_1, In_0} = 4'b0001;
        @(negedge clk);
        test_all_combos();

        #20 $finish;
    end

    // Task to loop through combinations and modes
    task test_all_combos;
        integer i;
        begin
            for (i = 0; i < 4; i = i + 1) begin
                f_sel = i; // Input combinations: 00, 01, 10, 11
                
                // Test Mode 1: Combinational Path
                is_synced = 0;
                #1; // Minor delay to allow combinational logic to propagate
                $display("Time=%0t | Comb Mode | f_sel=%b | out=%b", $time, f_sel, out);
                
                // Test Mode 2: Registered / Synchronous Path
                is_synced = 1;
                @(negedge clk); // Wait for the positive edge to clock data into FF, evaluate on negative edge
                $display("Time=%0t | Sync Mode | f_sel=%b | out_ff=%b", $time, f_sel, out_ff);
            end
        end
    endtask
endmodule

Lab 6/k_lut.vcd
$date
	Fri Apr 24 20:37:05 2026
$end
$version
	Icarus Verilog
$end
$timescale
	1ps
$end
$scope module k_lut_tb $end
$var wire 1 ! out_ff $end
$var wire 1 " out $end
$var reg 1 # In_0 $end
$var reg 1 $ In_1 $end
$var reg 1 % In_2 $end
$var reg 1 & In_3 $end
$var reg 1 ' clk $end
$var reg 2 ( f_sel [1:0] $end
$var reg 1 ) is_synced $end
$scope module uut $end
$var wire 1 # In_0 $end
$var wire 1 $ In_1 $end
$var wire 1 % In_2 $end
$var wire 1 & In_3 $end
$var wire 1 ' clk $end
$var wire 2 * f_sel [1:0] $end
$var wire 1 ) is_synced $end
$var wire 1 ! out_ff $end
$var wire 1 " out $end
$var wire 1 + mux_out $end
$var wire 1 , dff_in $end
$var wire 4 - config_data [3:0] $end
$scope module demux_inst $end
$var wire 1 ) sel $end
$var wire 1 + in $end
$var reg 1 " out0 $end
$var reg 1 , out1 $end
$upscope $end
$scope module dff_inst $end
$var wire 1 ' clk $end
$var wire 1 , d $end
$var reg 1 ! q $end
$upscope $end
$scope module mux_inst $end
$var wire 2 . sel [1:0] $end
$var wire 4 / data [3:0] $end
$var reg 1 + out $end
$upscope $end
$scope module sr_inst $end
$var wire 1 ' clk $end
$var wire 1 # in_0 $end
$var wire 1 $ in_1 $end
$var wire 1 % in_2 $end
$var wire 1 & in_3 $end
$var reg 4 0 q [3:0] $end
$upscope $end
$upscope $end
$scope task test_all_combos $end
$var integer 32 1 i [31:0] $end
$upscope $end
$upscope $end
$enddefinitions $end
$comment Show the parameter values. $end
$dumpall
$end
#0
$dumpvars
bx 1
bx 0
bx /
b0 .
bx -
0,
x+
b0 *
0)
b0 (
0'
0&
0%
0$
0#
x"
x!
$end
#5000
0"
0+
b0 -
b0 /
b0 0
0!
1'
#10000
1&
0'
#15000
b1000 -
b1000 /
b1000 0
1'
#20000
b0 1
0'
#21000
1)
#25000
1'
#30000
0)
b1 (
b1 *
b1 .
b1 1
0'
#31000
1)
#35000
1'
#40000
0)
b10 (
b10 *
b10 .
b10 1
0'
#41000
1)
#45000
1'
#50000
1"
1+
0)
b11 (
b11 *
b11 .
b11 1
0'
#51000
1,
0"
1)
#55000
1!
1'
#60000
1%
1$
b100 1
0'
#65000
b1110 -
b1110 /
b1110 0
1'
#70000
0,
0+
0)
b0 (
b0 *
b0 .
b0 1
0'
#71000
1)
#75000
0!
1'
#80000
1"
1+
0)
b1 (
b1 *
b1 .
b1 1
0'
#81000
1,
0"
1)
#85000
1!
1'
#90000
0,
1"
0)
b10 (
b10 *
b10 .
b10 1
0'
#91000
1,
0"
1)
#95000
1'
#100000
0,
1"
0)
b11 (
b11 *
b11 .
b11 1
0'
#101000
1,
0"
1)
#105000
1'
#110000
0&
1#
b100 1
0'
#115000
0,
0+
b111 -
b111 /
b111 0
1'
#120000
1"
1+
0)
b0 (
b0 *
b0 .
b0 1
0'
#121000
1,
0"
1)
#125000
1'
#130000
0,
1"
0)
b1 (
b1 *
b1 .
b1 1
0'
#131000
1,
0"
1)
#135000
1'
#140000
0,
1"
0)
b10 (
b10 *
b10 .
b10 1
0'
#141000
1,
0"
1)
#145000
1'
#150000
0,
0+
0)
b11 (
b11 *
b11 .
b11 1
0'
#151000
1)
#155000
0!
1'
#160000
0%
0$
b100 1
0'
#165000
b1 -
b1 /
b1 0
1'
#170000
1"
1+
0)
b0 (
b0 *
b0 .
b0 1
0'
#171000
1,
0"
1)
#175000
1!
1'
#180000
0,
0+
0)
b1 (
b1 *
b1 .
b1 1
0'
#181000
1)
#185000
0!
1'
#190000
0)
b10 (
b10 *
b10 .
b10 1
0'
#191000
1)
#195000
1'
#200000
0)
b11 (
b11 *
b11 .
b11 1
0'
#201000
1)
#205000
1'
#210000
b100 1
0'
