Lab 5/FIFO_MEM.v
module FIFO_MEM (
    input wire wr_clk,
    input wire [7:0] W_DATA,
    input wire wr_en,
    input wire full,
    input wire [4:0] wrt_ptr,
    input wire [4:0] rd_ptr,
    output wire [7:0] RD_DATA
);

reg [7:0] mem [0:15];

always @(posedge wr_clk) begin
 if (wr_en && !full) begin
  mem[wrt_ptr [3:0]] <= W_DATA;
  end
 else
  begin
// mem[wrt_ptr] <= mem[wrt_ptr]; 
  end
end

assign RD_DATA = mem[rd_ptr[3:0]];

endmodule

Lab 4/fifo_prove/src/Compare_ptrs.v
module Compare_ptrs (
    input wire [4:0] wrt_ptr_unsyn,
    input wire [4:0] wrt_ptr_2ff_syn,
    input wire [4:0] rd_ptr_unsyn,
     input wire [4:0] rd_ptr_2ff_syn,
    output wire empty,
    output wire full
);

assign empty = (wrt_ptr_2ff_syn == rd_ptr_unsyn) ? 1'b1 : 1'b0;
assign full = ((rd_ptr_2ff_syn[4:3]!=wrt_ptr_unsyn[4:3]) && (rd_ptr_2ff_syn[2:0] == wrt_ptr_unsyn[2:0])) ? 1'b1 : 1'b0;

endmodule

Lab 5/DD_SYN.v
module DD_SYN (
    input wire clk,
    input wire rst_n,
    input wire [4:0] unsync_data,
    output reg [4:0] sync_data
);

reg [4:0] sync1 ;

always @(posedge clk or negedge rst_n)
 begin
  if (!rst_n)begin
   sync1 <= 5'b0;
   sync_data <= 5'b0; 
  end
  else begin
   sync1 <= unsync_data;
   sync_data <= sync1;
  end
 end
   

endmodule

Lab 4/fifo_prove/src/rd_ptr_empty.v
module rd_ptr_empty (
    input wire clk,
    input wire rst,
    input wire rd_en,
    input wire empty,
    output wire rd_empty,
    output reg [4:0] rd_ptr,
    output wire [4:0] rd_ptr_gray
);

always @(posedge clk or negedge rst)
 begin
  if (!rst)
  begin
   rd_ptr <= 5'b0;
  end
  else if (rd_en && !empty)
  begin
   rd_ptr <= rd_ptr + 1'b1;
  end
 end

 assign rd_empty = empty;
 assign rd_ptr_gray = (rd_ptr >> 1) ^ rd_ptr;


endmodule

Lab 5/wrt_ptr_full.v
module wrt_ptr_full (
    input wire clk,
    input wire rst_n,
    input wire w_en,
    input wire full,
    output reg [4:0] wrt_ptr,
    output wire [4:0] wrt_ptr_gray,
    output wire w_full
);

always @ (posedge clk or negedge rst_n) begin
  if (!rst_n)
  begin
  wrt_ptr <= 5'b0;
  end
  else if (w_en && !full) begin
  wrt_ptr <= wrt_ptr + 1'b1;
  end
end

assign w_full = full;
assign wrt_ptr_gray = (wrt_ptr >> 1) ^ wrt_ptr;

endmodule

Lab 4/fifo_cover/src/FIFO_TOP.v
module FIFO_TOP (
    input wire wrt_clk,
    input wire wrt_rst,
    input wire w_en,
    input wire [7:0] wr_data,
    output wire w_full,

    input wire rd_clk,
    input wire rd_rst,
    input wire rd_en,
    output wire [7:0] rd_data,
    output wire rd_empty
);

wire full;
wire [4:0] wrt_ptr , wrt_ptr_gray , wrt_ptr_2ff_syn;

wire empty;
wire [4:0] rd_ptr, rd_ptr_gray , rd_ptr_2ff_syn;

wrt_ptr_full wr_p (
    .clk(wrt_clk),
    .rst_n(wrt_rst),
    .w_en(w_en),
    .full(full),
    .wrt_ptr(wrt_ptr),
    .wrt_ptr_gray(wrt_ptr_gray),
    .w_full(w_full)
);

rd_ptr_empty rd_p (
    .clk(rd_clk),
    .rst(rd_rst),
    .rd_en(rd_en),
    .empty(empty),
    .rd_empty(rd_empty),
    .rd_ptr(rd_ptr),
    .rd_ptr_gray(rd_ptr_gray)
);

DD_SYN ff_s1(
    .clk(rd_clk),
    .rst_n(rd_rst),
    .unsync_data(wrt_ptr_gray),
    .sync_data(wrt_ptr_2ff_syn)
);

DD_SYN ff_s2(
    .clk(wrt_clk),
    .rst_n(wrt_rst),
    .unsync_data(rd_ptr_gray),
    .sync_data(rd_ptr_2ff_syn)
);

Compare_ptrs c_ptr(
    .wrt_ptr_unsyn(wrt_ptr_gray),
    .wrt_ptr_2ff_syn(wrt_ptr_2ff_syn),
    .rd_ptr_unsyn(rd_ptr_gray),
    .rd_ptr_2ff_syn(rd_ptr_2ff_syn),
    .empty(empty),
    .full(full)
);

FIFO_MEM mem (
    .wr_clk(wrt_clk),
    .W_DATA(wr_data),
    .wr_en(w_en),
    .full(full),
    .wrt_ptr(wrt_ptr),
    .rd_ptr(rd_ptr),
    .RD_DATA(rd_data)
);






endmodule

Lab 4/FIFO_TOP_TB.v
module FIFO_TOP_TB();

reg wrt_clk;
reg wrt_rst;
reg w_en;
reg [7:0] wr_data;
wire w_full;
reg rd_clk;
reg rd_rst;
reg rd_en;
wire [7:0] rd_data;
wire rd_empty;

FIFO_TOP dut (
    .wrt_clk(wrt_clk),
    .wrt_rst(wrt_rst),
    .w_en(w_en),
    .wr_data(wr_data),
    .w_full(w_full),
    .rd_clk(rd_clk),
    .rd_rst(rd_rst),
    .rd_en(rd_en),
    .rd_data(rd_data),
    .rd_empty(rd_empty)
);

always #5 wrt_clk = ~wrt_clk;
always #10 rd_clk = ~rd_clk;

initial begin
    $dumpfile ("FIFO_TOP_TB.vcd");
    $dumpvars(0, FIFO_TOP_TB);
    wrt_clk = 0;
    rd_clk = 0;
    wrt_rst = 1;
    rd_rst = 1;
    w_en = 0;
    rd_en = 0;
    wr_data = 8'b0;

    #10;
    wrt_rst = 0;
    rd_rst = 0;

    #10;
    wrt_rst = 1;
    rd_rst = 1;

    #20;
    w_en = 1;
    wr_data = 8'hA5;

    #20;
    w_en = 0;

    #20;
    rd_en = 1;

    #40;
    rd_en = 0;

    #20;
    $finish;

end
endmodule

Lab 4/FIFO_TOP_TB.vcd
$date
	Sat Mar 14 17:20:15 2026
$end
$version
	Icarus Verilog
$end
$timescale
	1s
$end
$scope module FIFO_TOP_TB $end
$var wire 1 ! w_full $end
$var wire 1 " rd_empty $end
$var wire 8 # rd_data [7:0] $end
$var reg 1 $ rd_clk $end
$var reg 1 % rd_en $end
$var reg 1 & rd_rst $end
$var reg 1 ' w_en $end
$var reg 8 ( wr_data [7:0] $end
$var reg 1 ) wrt_clk $end
$var reg 1 * wrt_rst $end
$scope module dut $end
$var wire 1 $ rd_clk $end
$var wire 1 % rd_en $end
$var wire 1 & rd_rst $end
$var wire 1 ' w_en $end
$var wire 8 + wr_data [7:0] $end
$var wire 1 ) wrt_clk $end
$var wire 1 * wrt_rst $end
$var wire 5 , wrt_ptr_gray [4:0] $end
$var wire 5 - wrt_ptr_2ff_syn [4:0] $end
$var wire 5 . wrt_ptr [4:0] $end
$var wire 1 ! w_full $end
$var wire 5 / rd_ptr_gray [4:0] $end
$var wire 5 0 rd_ptr_2ff_syn [4:0] $end
$var wire 5 1 rd_ptr [4:0] $end
$var wire 1 " rd_empty $end
$var wire 8 2 rd_data [7:0] $end
$var wire 1 3 full $end
$var wire 1 4 empty $end
$scope module c_ptr $end
$var wire 5 5 wrt_ptr_unsyn [4:0] $end
$var wire 5 6 wrt_ptr_2ff_syn [4:0] $end
$var wire 5 7 rd_ptr_unsyn [4:0] $end
$var wire 5 8 rd_ptr_2ff_syn [4:0] $end
$var wire 1 3 full $end
$var wire 1 4 empty $end
$upscope $end
$scope module ff_s1 $end
$var wire 1 $ clk $end
$var wire 1 & rst_n $end
$var wire 5 9 unsync_data [4:0] $end
$var reg 5 : sync1 [4:0] $end
$var reg 5 ; sync_data [4:0] $end
$upscope $end
$scope module ff_s2 $end
$var wire 1 ) clk $end
$var wire 1 * rst_n $end
$var wire 5 < unsync_data [4:0] $end
$var reg 5 = sync1 [4:0] $end
$var reg 5 > sync_data [4:0] $end
$upscope $end
$scope module mem $end
$var wire 8 ? RD_DATA [7:0] $end
$var wire 8 @ W_DATA [7:0] $end
$var wire 1 3 full $end
$var wire 1 ) wr_clk $end
$var wire 1 ' wr_en $end
$var wire 5 A wrt_ptr [4:0] $end
$var wire 5 B rd_ptr [4:0] $end
$upscope $end
$scope module rd_p $end
$var wire 1 $ clk $end
$var wire 1 4 empty $end
$var wire 1 " rd_empty $end
$var wire 1 % rd_en $end
$var wire 5 C rd_ptr_gray [4:0] $end
$var wire 1 & rst $end
$var reg 5 D rd_ptr [4:0] $end
$upscope $end
$scope module wr_p $end
$var wire 1 ) clk $end
$var wire 1 3 full $end
$var wire 1 * rst_n $end
$var wire 1 ' w_en $end
$var wire 1 ! w_full $end
$var wire 5 E wrt_ptr_gray [4:0] $end
$var reg 5 F wrt_ptr [4:0] $end
$upscope $end
$upscope $end
$upscope $end
$enddefinitions $end
$comment Show the parameter values. $end
$dumpall
$end
#0
$dumpvars
bx F
bx E
bx D
bx C
bx B
bx A
b0 @
bx ?
bx >
bx =
bx <
bx ;
bx :
bx 9
bx 8
bx 7
bx 6
bx 5
x4
x3
bx 2
bx 1
bx 0
bx /
bx .
bx -
bx ,
b0 +
1*
0)
b0 (
0'
1&
0%
0$
bx #
x"
x!
$end
#5
1)
#10
0!
03
1"
14
b0 ,
b0 5
b0 9
b0 E
b0 /
b0 7
b0 <
b0 C
b0 0
b0 8
b0 >
b0 =
b0 .
b0 A
b0 F
b0 1
b0 B
b0 D
b0 -
b0 6
b0 ;
b0 :
0)
0&
0*
1$
#15
1)
#20
0)
1&
1*
0$
#25
1)
#30
0)
1$
#35
1)
#40
0)
0$
b10100101 (
b10100101 +
b10100101 @
1'
#45
b1 ,
b1 5
b1 9
b1 E
b1 .
b1 A
b1 F
b10100101 #
b10100101 2
b10100101 ?
1)
#50
b1 :
0)
1$
#55
b11 ,
b11 5
b11 9
b11 E
b10 .
b10 A
b10 F
1)
#60
0)
0$
0'
#65
1)
#70
0"
04
b1 -
b1 6
b1 ;
b11 :
0)
1$
#75
1)
#80
0)
0$
1%
#85
1)
#90
b1 /
b1 7
b1 <
b1 C
b1 1
b1 B
b1 D
b11 -
b11 6
b11 ;
0)
1$
#95
b1 =
1)
#100
0)
0$
#105
b1 0
b1 8
b1 >
1)
#110
1"
14
bx #
bx 2
bx ?
b11 /
b11 7
b11 <
b11 C
b10 1
b10 B
b10 D
0)
1$
#115
b11 =
1)
#120
0)
0$
0%
#125
b11 0
b11 8
b11 >
1)
