Lab 4/read_consumer.v
module read_consumer (
    input clk,
    input rst_n,
    input wire rd_empty,
    input wire [7:0] rd_data,
    output reg rd_en
);

always @(posedge clk or negedge rst_n)
 begin
  if (!rst_n)begin
   rd_en <= 1'b0;
  end
  else if (!rd_empty)
  begin
   rd_en <= 1'b1;
  end
  else
  begin
   rd_en <= 1'b0;
  end
end


endmodule

Lab 5/FIFO_MEM.v
module FIFO_MEM (
    input wire wr_clk,
    input wire [7:0] W_DATA,
    input wire wr_en,
    input wire full,
    input wire [4:0] wrt_ptr,
    input wire [4:0] rd_ptr,
    output wire [7:0] RD_DATA
);

reg [7:0] mem [0:15];

always @(posedge wr_clk) begin
 if (wr_en && !full) begin
  mem[wrt_ptr [3:0]] <= W_DATA;
  end
 else
  begin
// mem[wrt_ptr] <= mem[wrt_ptr]; 
  end
end

assign RD_DATA = mem[rd_ptr[3:0]];

endmodule

Lab 4/fifo_prove/src/Compare_ptrs.v
module Compare_ptrs (
    input wire [4:0] wrt_ptr_unsyn,
    input wire [4:0] wrt_ptr_2ff_syn,
    input wire [4:0] rd_ptr_unsyn,
     input wire [4:0] rd_ptr_2ff_syn,
    output wire empty,
    output wire full
);

assign empty = (wrt_ptr_2ff_syn == rd_ptr_unsyn) ? 1'b1 : 1'b0;
assign full = ((rd_ptr_2ff_syn[4:3]!=wrt_ptr_unsyn[4:3]) && (rd_ptr_2ff_syn[2:0] == wrt_ptr_unsyn[2:0])) ? 1'b1 : 1'b0;

endmodule

Lab 5/DD_SYN.v
module DD_SYN (
    input wire clk,
    input wire rst_n,
    input wire [4:0] unsync_data,
    output reg [4:0] sync_data
);

reg [4:0] sync1 ;

always @(posedge clk or negedge rst_n)
 begin
  if (!rst_n)begin
   sync1 <= 5'b0;
   sync_data <= 5'b0; 
  end
  else begin
   sync1 <= unsync_data;
   sync_data <= sync1;
  end
 end
   

endmodule

Lab 4/fifo_prove/src/rd_ptr_empty.v
module rd_ptr_empty (
    input wire clk,
    input wire rst,
    input wire rd_en,
    input wire empty,
    output wire rd_empty,
    output reg [4:0] rd_ptr,
    output wire [4:0] rd_ptr_gray
);

always @(posedge clk or negedge rst)
 begin
  if (!rst)
  begin
   rd_ptr <= 5'b0;
  end
  else if (rd_en && !empty)
  begin
   rd_ptr <= rd_ptr + 1'b1;
  end
 end

 assign rd_empty = empty;
 assign rd_ptr_gray = (rd_ptr >> 1) ^ rd_ptr;


endmodule

Lab 5/wrt_ptr_full.v
module wrt_ptr_full (
    input wire clk,
    input wire rst_n,
    input wire w_en,
    input wire full,
    output reg [4:0] wrt_ptr,
    output wire [4:0] wrt_ptr_gray,
    output wire w_full
);

always @ (posedge clk or negedge rst_n) begin
  if (!rst_n)
  begin
  wrt_ptr <= 5'b0;
  end
  else if (w_en && !full) begin
  wrt_ptr <= wrt_ptr + 1'b1;
  end
end

assign w_full = full;
assign wrt_ptr_gray = (wrt_ptr >> 1) ^ wrt_ptr;

endmodule

Lab 4/fifo_cover/src/FIFO_TOP.v
module FIFO_TOP (
    input wire wrt_clk,
    input wire wrt_rst,
    input wire w_en,
    input wire [7:0] wr_data,
    output wire w_full,

    input wire rd_clk,
    input wire rd_rst,
    input wire rd_en,
    output wire [7:0] rd_data,
    output wire rd_empty
);

wire full;
wire [4:0] wrt_ptr , wrt_ptr_gray , wrt_ptr_2ff_syn;

wire empty;
wire [4:0] rd_ptr, rd_ptr_gray , rd_ptr_2ff_syn;

wrt_ptr_full wr_p (
    .clk(wrt_clk),
    .rst_n(wrt_rst),
    .w_en(w_en),
    .full(full),
    .wrt_ptr(wrt_ptr),
    .wrt_ptr_gray(wrt_ptr_gray),
    .w_full(w_full)
);

rd_ptr_empty rd_p (
    .clk(rd_clk),
    .rst(rd_rst),
    .rd_en(rd_en),
    .empty(empty),
    .rd_empty(rd_empty),
    .rd_ptr(rd_ptr),
    .rd_ptr_gray(rd_ptr_gray)
);

DD_SYN ff_s1(
    .clk(rd_clk),
    .rst_n(rd_rst),
    .unsync_data(wrt_ptr_gray),
    .sync_data(wrt_ptr_2ff_syn)
);

DD_SYN ff_s2(
    .clk(wrt_clk),
    .rst_n(wrt_rst),
    .unsync_data(rd_ptr_gray),
    .sync_data(rd_ptr_2ff_syn)
);

Compare_ptrs c_ptr(
    .wrt_ptr_unsyn(wrt_ptr_gray),
    .wrt_ptr_2ff_syn(wrt_ptr_2ff_syn),
    .rd_ptr_unsyn(rd_ptr_gray),
    .rd_ptr_2ff_syn(rd_ptr_2ff_syn),
    .empty(empty),
    .full(full)
);

FIFO_MEM mem (
    .wr_clk(wrt_clk),
    .W_DATA(wr_data),
    .wr_en(w_en),
    .full(full),
    .wrt_ptr(wrt_ptr),
    .rd_ptr(rd_ptr),
    .RD_DATA(rd_data)
);






endmodule

Lab 4/write_producer.v
module write_producer (
    input wire clk,
    input wire rst_n,
    input wire full,
    input wire start,
    output reg w_en,
    output reg [7:0] wr_data
);

/*always @(posedge clk or negedge rst_n) begin
  if (!rst_n) begin
    wr_data <= 8'b0;
    w_en <= 0;
  end else if (!full) begin
    wr_data <= wr_data + 1'b1;
  end else begin
    wr_data <= wr_data; // Hold the data when full
  end */

localparam IDLE = 3'b000,
           S1 = 3'b001,
           S2 = 3'b010,
           S3 = 3'b011,
           S4 = 3'b100;

reg [2:0] current_state, next_state;

always @(posedge clk or negedge rst_n) begin
    if (!rst_n) begin
        current_state <= IDLE;
    end else begin
        current_state <= next_state;
    end
end

always @(*)begin
  case(current_state)
    IDLE: begin
      wr_data = 8'b0;
      w_en = 0;
      if (full)
        next_state = IDLE;
      else if (start)
        next_state = S1;
      else
        next_state = IDLE;
    end
    S1: begin
      wr_data = 8'hAD; // Example data to write
      w_en = 1;
      if (full)
        next_state = IDLE;
      else
        next_state = S2;
    end
    S2: begin
      wr_data = 8'h5A; // Example data to write
      w_en = 1;
      if (full)
        next_state = IDLE;
      else
        next_state = S3;
    end
    S3: begin
      wr_data = 8'hFF; // Example data to write
      w_en = 1;
      if (full)
        next_state = IDLE;
      else
        next_state = S4;
    end
    S4: begin
      wr_data = 8'h00; // Example data to write
      w_en = 1;
      if (full)
        next_state = IDLE;
      else
        next_state = IDLE;
    end
    default: begin
      wr_data = 8'b0;
      w_en = 0;
      next_state = IDLE;
    end
    
  endcase
end




endmodule

Lab 4/FIFO_TOP_TOP.v
module FIFO_TOP_TOP (
    input wire wrt_clk,
    input wire wrt_rst,
    input wire start,

    input wire rd_clk,
    input wire rd_rst
);

wire w_en;
wire [7:0] wr_data;
wire w_full;

wire rd_en;
wire [7:0] rd_data;
wire rd_empty;



write_producer wr_prd (
    .clk(wrt_clk),
    .rst_n(wrt_rst),
    .full(w_full),
    .start(start),
    .w_en(w_en),
    .wr_data(wr_data)
);

FIFO_TOP dut (
    .wrt_clk(wrt_clk),
    .wrt_rst(wrt_rst),
    .w_en(w_en),
    .wr_data(wr_data),
    .w_full(w_full),
    .rd_clk(rd_clk),
    .rd_rst(rd_rst),
    .rd_en(rd_en),
    .rd_data(rd_data),
    .rd_empty(rd_empty)
);

read_consumer rd_csm (
    .clk(rd_clk),
    .rst_n(rd_rst),
    .rd_empty(rd_empty),
    .rd_data(rd_data),
    .rd_en(rd_en)
);







endmodule

Lab 4/FIFO_TOP_TOP_TB.v
module FIFO_TOP_TOP_TB();

reg wrt_clk;
reg wrt_rst;
reg start;
reg rd_clk;
reg rd_rst;

FIFO_TOP_TOP dut (
    .wrt_clk(wrt_clk),
    .wrt_rst(wrt_rst),
    .start(start),
    .rd_clk(rd_clk),
    .rd_rst(rd_rst)
);

always #5 wrt_clk = ~wrt_clk;
always #10 rd_clk = ~rd_clk;

initial begin
   $dumpfile ("FIFO.vcd");
   $dumpvars(0, FIFO_TOP_TOP_TB);
    wrt_clk = 0;
    rd_clk = 0;
    wrt_rst = 1;
    rd_rst = 1;
    start = 0;

    #10;
    wrt_rst = 0;
    rd_rst = 0;

    #10;
    wrt_rst = 1;
    rd_rst = 1;

    #20;
    start = 1;

    #20;
    start = 0;

    #100;
    $finish;

end
endmodule

Lab 4/FIFO.vcd
$date
	Sat Mar 14 19:51:24 2026
$end
$version
	Icarus Verilog
$end
$timescale
	1s
$end
$scope module FIFO_TOP_TOP_TB $end
$var reg 1 ! rd_clk $end
$var reg 1 " rd_rst $end
$var reg 1 # start $end
$var reg 1 $ wrt_clk $end
$var reg 1 % wrt_rst $end
$scope module dut $end
$var wire 1 ! rd_clk $end
$var wire 1 " rd_rst $end
$var wire 1 # start $end
$var wire 1 $ wrt_clk $end
$var wire 1 % wrt_rst $end
$var wire 8 & wr_data [7:0] $end
$var wire 1 ' w_full $end
$var wire 1 ( w_en $end
$var wire 1 ) rd_en $end
$var wire 1 * rd_empty $end
$var wire 8 + rd_data [7:0] $end
$scope module dut $end
$var wire 1 ! rd_clk $end
$var wire 1 " rd_rst $end
$var wire 1 $ wrt_clk $end
$var wire 1 % wrt_rst $end
$var wire 5 , wrt_ptr_gray [4:0] $end
$var wire 5 - wrt_ptr_2ff_syn [4:0] $end
$var wire 5 . wrt_ptr [4:0] $end
$var wire 8 / wr_data [7:0] $end
$var wire 1 ' w_full $end
$var wire 1 ( w_en $end
$var wire 5 0 rd_ptr_gray [4:0] $end
$var wire 5 1 rd_ptr_2ff_syn [4:0] $end
$var wire 5 2 rd_ptr [4:0] $end
$var wire 1 ) rd_en $end
$var wire 1 * rd_empty $end
$var wire 8 3 rd_data [7:0] $end
$var wire 1 4 full $end
$var wire 1 5 empty $end
$scope module c_ptr $end
$var wire 5 6 wrt_ptr_unsyn [4:0] $end
$var wire 5 7 wrt_ptr_2ff_syn [4:0] $end
$var wire 5 8 rd_ptr_unsyn [4:0] $end
$var wire 5 9 rd_ptr_2ff_syn [4:0] $end
$var wire 1 4 full $end
$var wire 1 5 empty $end
$upscope $end
$scope module ff_s1 $end
$var wire 1 ! clk $end
$var wire 1 " rst_n $end
$var wire 5 : unsync_data [4:0] $end
$var reg 5 ; sync1 [4:0] $end
$var reg 5 < sync_data [4:0] $end
$upscope $end
$scope module ff_s2 $end
$var wire 1 $ clk $end
$var wire 1 % rst_n $end
$var wire 5 = unsync_data [4:0] $end
$var reg 5 > sync1 [4:0] $end
$var reg 5 ? sync_data [4:0] $end
$upscope $end
$scope module mem $end
$var wire 8 @ RD_DATA [7:0] $end
$var wire 1 4 full $end
$var wire 1 $ wr_clk $end
$var wire 5 A wrt_ptr [4:0] $end
$var wire 1 ( wr_en $end
$var wire 5 B rd_ptr [4:0] $end
$var wire 8 C W_DATA [7:0] $end
$upscope $end
$scope module rd_p $end
$var wire 1 ! clk $end
$var wire 1 5 empty $end
$var wire 1 * rd_empty $end
$var wire 5 D rd_ptr_gray [4:0] $end
$var wire 1 " rst $end
$var wire 1 ) rd_en $end
$var reg 5 E rd_ptr [4:0] $end
$upscope $end
$scope module wr_p $end
$var wire 1 $ clk $end
$var wire 1 4 full $end
$var wire 1 % rst_n $end
$var wire 1 ' w_full $end
$var wire 5 F wrt_ptr_gray [4:0] $end
$var wire 1 ( w_en $end
$var reg 5 G wrt_ptr [4:0] $end
$upscope $end
$upscope $end
$scope module rd_csm $end
$var wire 1 ! clk $end
$var wire 8 H rd_data [7:0] $end
$var wire 1 * rd_empty $end
$var wire 1 " rst_n $end
$var reg 1 ) rd_en $end
$upscope $end
$scope module wr_prd $end
$var wire 1 $ clk $end
$var wire 1 ' full $end
$var wire 1 % rst_n $end
$var wire 1 # start $end
$var parameter 3 I IDLE $end
$var parameter 3 J S1 $end
$var parameter 3 K S2 $end
$var parameter 3 L S3 $end
$var parameter 3 M S4 $end
$var reg 3 N current_state [2:0] $end
$var reg 3 O next_state [2:0] $end
$var reg 1 ( w_en $end
$var reg 8 P wr_data [7:0] $end
$upscope $end
$upscope $end
$upscope $end
$enddefinitions $end
$comment Show the parameter values. $end
$dumpall
b100 M
b11 L
b10 K
b1 J
b0 I
$end
#0
$dumpvars
b0 P
b0 O
bx N
bx H
bx G
bx F
bx E
bx D
b0 C
bx B
bx A
bx @
bx ?
bx >
bx =
bx <
bx ;
bx :
bx 9
bx 8
bx 7
bx 6
x5
x4
bx 3
bx 2
bx 1
bx 0
b0 /
bx .
bx -
bx ,
bx +
x*
x)
0(
x'
b0 &
1%
0$
0#
1"
0!
$end
#5
b0 N
1$
#10
0'
04
1*
15
b0 ,
b0 6
b0 :
b0 F
b0 0
b0 8
b0 =
b0 D
b0 1
b0 9
b0 ?
b0 >
b0 .
b0 A
b0 G
b0 2
b0 B
b0 E
b0 -
b0 7
b0 <
b0 ;
0)
0$
0"
0%
1!
#15
1$
#20
0$
1"
1%
0!
#25
1$
#30
0$
1!
#35
1$
#40
b1 O
0$
0!
1#
#45
b10 O
1(
b10101101 &
b10101101 /
b10101101 C
b10101101 P
b1 N
1$
#50
0$
1!
#55
b11 O
b1011010 &
b1011010 /
b1011010 C
b1011010 P
b1 ,
b1 6
b1 :
b1 F
b10 N
b1 .
b1 A
b1 G
b10101101 +
b10101101 3
b10101101 @
b10101101 H
1$
#60
0$
0!
0#
#65
b11 ,
b11 6
b11 :
b11 F
b100 O
b11111111 &
b11111111 /
b11111111 C
b11111111 P
b10 .
b10 A
b10 G
b11 N
1$
#70
b11 ;
0$
1!
#75
b0 O
b0 &
b0 /
b0 C
b0 P
b10 ,
b10 6
b10 :
b10 F
b100 N
b11 .
b11 A
b11 G
1$
#80
0$
0!
#85
b110 ,
b110 6
b110 :
b110 F
0(
b100 .
b100 A
b100 G
b0 N
1$
#90
0*
05
b11 -
b11 7
b11 <
b110 ;
0$
1!
#95
1$
#100
0$
0!
#105
1$
#110
1)
b110 -
b110 7
b110 <
0$
1!
#115
1$
#120
0$
0!
#125
1$
#130
b1011010 +
b1011010 3
b1011010 @
b1011010 H
b1 0
b1 8
b1 =
b1 D
b1 2
b1 B
b1 E
0$
1!
#135
b1 >
1$
#140
0$
0!
#145
b1 1
b1 9
b1 ?
1$
#150
b11111111 +
b11111111 3
b11111111 @
b11111111 H
b11 0
b11 8
b11 =
b11 D
b10 2
b10 B
b10 E
0$
1!
#155
b11 >
1$
